BintoDec/bintodec.v
module binary_to_decimal(
  input [7:0] binary,
  output reg [7:0]decimal
);
//reg[7:0]temp=0;
//reg [7:0] intermediate; 
integer i, j, k,temp;
always @(binary) begin
k=0;
for (i=0; i<8; i++)
begin
j=binary[i];
temp=j*(2**i);
k=k+temp;
end
decimal=k;
end
/*intermediate=binary;
    for (i = 0; i <8; i = i + 1) begin
      if (intermediate[i] == 1) 
      begin
        temp = temp+2**i;
        //$display("temp: %d", temp);
      end
    end
end
assign decimal=temp;*/
endmodule

BintoDec/tb_bintodec.v
`include "bintodec.v" // adding design file
module tb;
reg [7:0] binary;
wire [7:0]decimal;


binary_to_decimal dut (.*); 
integer i;
/*reg [7:0] a[0:12]; 
initial begin
a[0]=8'b00000001;
a[1]=8'b00000010;
a[2]=8'b00000011;
a[3]=8'b00000100;
a[4]=8'b00000101;
a[5]=8'b00000110;
a[6]=8'b00000111;
a[7]=8'b00001000;
a[8]=8'b00001001;
a[9]=8'b00001010;
a[10]=8'b11111110;
a[11]=8'b10101010;
a[12]=8'b10101011;
end*/

initial begin
for (i = 0; i <13; i= i+1) begin
binary =$urandom_range(0,255);
#30;
$display("Decimal: %d Binary: %b", decimal, binary);
end
end
initial begin
    $dumpfile("test.vcd");
    $dumpvars(0,tb);
end
endmodule

BintoDec/test.vcd
$date
	Tue Feb 28 11:13:12 2023
$end
$version
	Icarus Verilog
$end
$timescale
	1s
$end
$scope module tb $end
$var wire 8 ! decimal [7:0] $end
$var reg 8 " binary [7:0] $end
$var integer 32 # i [31:0] $end
$scope module dut $end
$var wire 8 $ binary [7:0] $end
$var reg 8 % decimal [7:0] $end
$var integer 32 & i [31:0] $end
$var integer 32 ' j [31:0] $end
$var integer 32 ( k [31:0] $end
$var integer 32 ) temp [31:0] $end
$upscope $end
$upscope $end
$enddefinitions $end
#0
$dumpvars
b10000000 )
b10010010 (
b1 '
b1000 &
b10010010 %
b10010010 $
b0 #
b10010010 "
b10010010 !
$end
#30
b1000000 !
b1000000 %
b0 )
b0 '
b1000 &
b1000000 (
b1000000 "
b1000000 $
b1 #
#60
b100 !
b100 %
b0 )
b0 '
b1000 &
b100 (
b100 "
b100 $
b10 #
#90
b110001 !
b110001 %
b0 )
b0 '
b1000 &
b110001 (
b110001 "
b110001 $
b11 #
#120
b10000110 !
b10000110 %
b10000000 )
b1 '
b1000 &
b10000110 (
b10000110 "
b10000110 $
b100 #
#150
b11000110 !
b11000110 %
b10000000 )
b1 '
b1000 &
b11000110 (
b11000110 "
b11000110 $
b101 #
#180
b110010 !
b110010 %
b0 )
b0 '
b1000 &
b110010 (
b110010 "
b110010 $
b110 #
#210
b1001 !
b1001 %
b0 )
b0 '
b1000 &
b1001 (
b1001 "
b1001 $
b111 #
#240
b10000000 !
b10000000 %
b10000000 )
b1 '
b1000 &
b10000000 (
b10000000 "
b10000000 $
b1000 #
#270
b10000110 !
b10000110 %
b10000000 )
b1 '
b1000 &
b10000110 (
b10000110 "
b10000110 $
b1001 #
#300
b10111011 !
b10111011 %
b1 '
b10000000 )
b1000 &
b10111011 (
b10111011 "
b10111011 $
b1010 #
#330
b10011110 !
b10011110 %
b10000000 )
b1 '
b1000 &
b10011110 (
b10011110 "
b10011110 $
b1011 #
#360
b11110110 !
b11110110 %
b10000000 )
b1 '
b1000 &
b11110110 (
b11110110 "
b11110110 $
b1100 #
#390
b1101 #
